AUTHORS.rst
CONTRIBUTING.rst
HISTORY.rst
LICENSE
MANIFEST.in
README.rst
setup.cfg
setup.py
docs/Makefile
docs/authors.rst
docs/conf.py
docs/contributing.rst
docs/history.rst
docs/index.rst
docs/installation.rst
docs/make.bat
docs/readme.rst
docs/usage.rst
lswarm/__init__.py
lswarm/cli.py
lswarm/lswarm.py
lswarm.egg-info/PKG-INFO
lswarm.egg-info/SOURCES.txt
lswarm.egg-info/dependency_links.txt
lswarm.egg-info/entry_points.txt
lswarm.egg-info/not-zip-safe
lswarm.egg-info/requires.txt
lswarm.egg-info/top_level.txt
tests/__init__.py
tests/test_lswarm.py